AUTHORS
LICENSE
MANIFEST.in
README.rst
requirements.txt
setup.py
version.py
alignak_module_external_commands/__init__.py
alignak_module_external_commands/external_commands.py
alignak_module_external_commands.egg-info/PKG-INFO
alignak_module_external_commands.egg-info/SOURCES.txt
alignak_module_external_commands.egg-info/dependency_links.txt
alignak_module_external_commands.egg-info/not-zip-safe
alignak_module_external_commands.egg-info/top_level.txt
alignak_module_external_commands/etc/__init__.py
alignak_module_external_commands/etc/arbiter/modules/mod-external-commands.cfg
alignak_module_external_commands/plugins/host-check.sh
alignak_module_external_commands/plugins/service-check.sh
test/test_module.py