Metadata-Version: 1.1
Name: alignak-module-external-commands
Version: 0.3.1
Summary: Alignak - Receiver module for the external commands named pipe file
Home-page: https://github.com/Alignak-monitoring-contrib/alignak-modules-external-commands
Author: Frédéric Mohier
Author-email: frederic.mohier@alignak.net
License: GNU Affero General Public License, version 3
Keywords: a,l,i,g,n,a,k, ,m,o,n,i,t,o,r,i,n,g, ,m,o,d,u,l,e, ,e,x,t,e,r,n,a,l,-,c,o,m,m,a,n,d,s
Platform: UNKNOWN
Classifier: Development Status :: 5 - Production/Stable
Classifier: Environment :: Console
Classifier: Intended Audience :: Developers
Classifier: Intended Audience :: System Administrators
Classifier: License :: OSI Approved :: GNU Affero General Public License v3 or later (AGPLv3+)
Classifier: Natural Language :: English
Classifier: Programming Language :: Python
Classifier: Topic :: System :: Monitoring
Classifier: Topic :: System :: Systems Administration
